{
  "$schema": "https://developer.microsoft.com/json-schemas/fabric/item/report/definition/visualContainer/2.10.0/schema.json",
  "name": "c4d288cd34251650d63a",
  "position": {
    "x": 13.249400479616327,
    "y": 51.843096951010622,
    "z": 10000,
    "height": 34.523809523809526,
    "width": 133.33333333333334,
    "tabOrder": 10000
  },
  "visual": {
    "visualType": "textbox",
    "objects": {
      "general": [
        {
          "properties": {
            "paragraphs": [
              {
                "textRuns": [
                  {
                    "value": "Vs Ano anterior",
                    "textStyle": {
                      "fontFamily": "Segoe UI",
                      "fontSize": "12pt",
                      "color": "#ffffff"
                    }
                  }
                ]
              }
            ]
          }
        }
      ]
    },
    "visualContainerObjects": {
      "background": [
        {
          "properties": {
            "show": {
              "expr": {
                "Literal": {
                  "Value": "false"
                }
              }
            }
          }
        }
      ]
    },
    "drillFilterOtherVisuals": true
  },
  "parentGroupName": "aa3232e684b011b41a5a"
}