{
  "$schema": "https://developer.microsoft.com/json-schemas/fabric/item/report/definition/visualContainer/2.10.0/schema.json",
  "name": "4631dc36e2c035b8252d",
  "position": {
    "x": 103.33333333333333,
    "y": 188.88888888888889,
    "z": 7000,
    "height": 238.88888888888889,
    "width": 715.55555555555554,
    "tabOrder": 4000
  },
  "visual": {
    "visualType": "areaChart",
    "query": {
      "queryState": {
        "Category": {
          "projections": [
            {
              "field": {
                "HierarchyLevel": {
                  "Expression": {
                    "Hierarchy": {
                      "Expression": {
                        "PropertyVariationSource": {
                          "Expression": {
                            "SourceRef": {
                              "Entity": "dCalendario"
                            }
                          },
                          "Name": "Variation",
                          "Property": "Inicio do Mês"
                        }
                      },
                      "Hierarchy": "Hierarquia de datas"
                    }
                  },
                  "Level": "Ano"
                }
              },
              "queryRef": "dCalendario.Inicio do Mês.Variation.Hierarquia de datas.Ano",
              "nativeQueryRef": "Inicio do Mês Ano",
              "active": true
            },
            {
              "field": {
                "HierarchyLevel": {
                  "Expression": {
                    "Hierarchy": {
                      "Expression": {
                        "PropertyVariationSource": {
                          "Expression": {
                            "SourceRef": {
                              "Entity": "dCalendario"
                            }
                          },
                          "Name": "Variation",
                          "Property": "Inicio do Mês"
                        }
                      },
                      "Hierarchy": "Hierarquia de datas"
                    }
                  },
                  "Level": "Trimestre"
                }
              },
              "queryRef": "dCalendario.Inicio do Mês.Variation.Hierarquia de datas.Trimestre",
              "nativeQueryRef": "Inicio do Mês Trimestre",
              "active": true
            },
            {
              "field": {
                "HierarchyLevel": {
                  "Expression": {
                    "Hierarchy": {
                      "Expression": {
                        "PropertyVariationSource": {
                          "Expression": {
                            "SourceRef": {
                              "Entity": "dCalendario"
                            }
                          },
                          "Name": "Variation",
                          "Property": "Inicio do Mês"
                        }
                      },
                      "Hierarchy": "Hierarquia de datas"
                    }
                  },
                  "Level": "Mês"
                }
              },
              "queryRef": "dCalendario.Inicio do Mês.Variation.Hierarquia de datas.Mês",
              "nativeQueryRef": "Inicio do Mês Mês",
              "active": true
            },
            {
              "field": {
                "HierarchyLevel": {
                  "Expression": {
                    "Hierarchy": {
                      "Expression": {
                        "PropertyVariationSource": {
                          "Expression": {
                            "SourceRef": {
                              "Entity": "dCalendario"
                            }
                          },
                          "Name": "Variation",
                          "Property": "Inicio do Mês"
                        }
                      },
                      "Hierarchy": "Hierarquia de datas"
                    }
                  },
                  "Level": "Dia"
                }
              },
              "queryRef": "dCalendario.Inicio do Mês.Variation.Hierarquia de datas.Dia",
              "nativeQueryRef": "Inicio do Mês Dia",
              "active": true
            }
          ]
        },
        "Y": {
          "projections": [
            {
              "field": {
                "Measure": {
                  "Expression": {
                    "SourceRef": {
                      "Entity": "Medidas"
                    }
                  },
                  "Property": "% Devoluções"
                }
              },
              "queryRef": "Medidas.% Devoluções",
              "nativeQueryRef": "% Devoluções"
            }
          ]
        }
      }
    },
    "objects": {
      "dataPoint": [
        {
          "properties": {
            "fill": {
              "solid": {
                "color": {
                  "expr": {
                    "Literal": {
                      "Value": "'#270067'"
                    }
                  }
                }
              }
            }
          },
          "selector": {
            "metadata": "Medidas.% Devoluções"
          }
        }
      ],
      "lineStyles": [
        {
          "properties": {
            "strokeLineJoin": {
              "expr": {
                "Literal": {
                  "Value": "'miter'"
                }
              }
            },
            "lineChartType": {
              "expr": {
                "Literal": {
                  "Value": "'smooth'"
                }
              }
            }
          }
        }
      ],
      "categoryAxis": [
        {
          "properties": {
            "showAxisTitle": {
              "expr": {
                "Literal": {
                  "Value": "false"
                }
              }
            },
            "labelColor": {
              "solid": {
                "color": {
                  "expr": {
                    "ThemeDataColor": {
                      "ColorId": 4,
                      "Percent": 0
                    }
                  }
                }
              }
            },
            "bold": {
              "expr": {
                "Literal": {
                  "Value": "false"
                }
              }
            },
            "fontFamily": {
              "expr": {
                "Literal": {
                  "Value": "'''Segoe UI'', wf_segoe-ui_normal, helvetica, arial, sans-serif'"
                }
              }
            },
            "fontSize": {
              "expr": {
                "Literal": {
                  "Value": "8D"
                }
              }
            }
          }
        }
      ],
      "valueAxis": [
        {
          "properties": {
            "showAxisTitle": {
              "expr": {
                "Literal": {
                  "Value": "false"
                }
              }
            },
            "labelColor": {
              "solid": {
                "color": {
                  "expr": {
                    "ThemeDataColor": {
                      "ColorId": 4,
                      "Percent": 0
                    }
                  }
                }
              }
            },
            "bold": {
              "expr": {
                "Literal": {
                  "Value": "true"
                }
              }
            }
          }
        }
      ]
    },
    "visualContainerObjects": {
      "title": [
        {
          "properties": {
            "text": {
              "expr": {
                "Literal": {
                  "Value": "'% Devoluções MoM'"
                }
              }
            },
            "fontColor": {
              "solid": {
                "color": {
                  "expr": {
                    "Literal": {
                      "Value": "'#270067'"
                    }
                  }
                }
              }
            },
            "fontFamily": {
              "expr": {
                "Literal": {
                  "Value": "'''Segoe UI'', wf_segoe-ui_normal, helvetica, arial, sans-serif'"
                }
              }
            },
            "bold": {
              "expr": {
                "Literal": {
                  "Value": "true"
                }
              }
            }
          }
        }
      ],
      "background": [
        {
          "properties": {
            "show": {
              "expr": {
                "Literal": {
                  "Value": "false"
                }
              }
            }
          }
        }
      ]
    },
    "drillFilterOtherVisuals": true
  }
}